clinitokenizer/__init__.py
clinitokenizer/tokenize.py
clinitokenizer-0.0.5.dist-info/LICENSE
clinitokenizer-0.0.5.dist-info/METADATA
clinitokenizer-0.0.5.dist-info/WHEEL
clinitokenizer-0.0.5.dist-info/top_level.txt
clinitokenizer-0.0.5.dist-info/RECORD
