Metadata-Version: 2.1
Name: clinitokenizer
Version: 0.0.5
Summary: Sentence tokenizer for text from clinical notes.
Home-page: https://github.com/clinisift/clinitokenizer
Author: Sam Rawal
Author-email: scrawal2@illinois.edu
Project-URL: Bug Tracker, https://github.com/clinisift/clinitokenizer/issues
Classifier: Programming Language :: Python :: 3
Classifier: License :: OSI Approved :: Apache Software License
Classifier: Operating System :: OS Independent
Requires-Python: >=3.6
License-File: LICENSE
Requires-Dist: setuptools (>=42)
Requires-Dist: torch
Requires-Dist: tqdm (>=4.62.3)
Requires-Dist: simpletransformers (==0.63.6)
Requires-Dist: transformers (==4.14.1)
Requires-Dist: spacy (==3.1.3)
